hash.py
hash_hound-0.3.dist-info/LICENSE
hash_hound-0.3.dist-info/METADATA
hash_hound-0.3.dist-info/WHEEL
hash_hound-0.3.dist-info/entry_points.txt
hash_hound-0.3.dist-info/top_level.txt
hash_hound-0.3.dist-info/RECORD
